MANIFEST.in
README
requirements.txt
setup.py
ltg/__init__.py
ltg/__main__.py
ltg/cli.py
ltg/core.py
ltg/exceptions.py
ltg/file_utils.py
ltg/git.py
ltg/linker.py
ltg/manager.py
ltg/sh.py
ltg/storage.py
ltg/utils.py
ltg/version.py
ltg.egg-info/PKG-INFO
ltg.egg-info/SOURCES.txt
ltg.egg-info/dependency_links.txt
ltg.egg-info/entry_points.txt
ltg.egg-info/pbr.json
ltg.egg-info/requires.txt
ltg.egg-info/top_level.txt