Metadata-Version: 1.1
Name: ltg
Version: 0.2.2
Summary: link to git
Home-page: https://bitbucket.org/afriemann/ltg
Author: Aljosha Friemann
Author-email: aljosha.friemann@gmail.com
License: UNKNOWN
Download-URL: https://pypi.python.org/pypi/ltg
Keywords: utility,configuration,git,linux
Platform: UNKNOWN
